inf_cl-1.2.1.dist-info/METADATA
inf_cl-1.2.1.dist-info/WHEEL
inf_cl-1.2.1.dist-info/entry_points.txt
inf_cl-1.2.1.dist-info/licenses/LICENSE
inf_cl/__init__.py
inf_cl/flash.py
inf_cl/ring.py
inf_cl-1.2.1.dist-info/RECORD
