Metadata-Version: 2.1
Name: inf-cl
Version: 1.2.1
Summary: A highly memory-efficient contrastive loss.
Author: Hang Zhang, Kehan Li, Xin Li
Author-Email: Zesen Cheng <cyanlaser@stu.pku.edu.cn>
License: MIT
Classifier: Development Status :: 4 - Beta
Classifier: Intended Audience :: Education
Classifier: Intended Audience :: Science/Research
Classifier: License :: OSI Approved :: MIT License
Classifier: Programming Language :: Python :: 3.8
Classifier: Programming Language :: Python :: 3.9
Classifier: Programming Language :: Python :: 3.10
Classifier: Programming Language :: Python :: 3.11
Classifier: Programming Language :: Python :: 3.12
Classifier: Topic :: Scientific/Engineering
Classifier: Topic :: Scientific/Engineering :: Artificial Intelligence
Classifier: Topic :: Software Development
Classifier: Topic :: Software Development :: Libraries
Classifier: Topic :: Software Development :: Libraries :: Python Modules
Project-URL: Homepage, https://github.com/DAMO-NLP-SG/Inf-CLIP
Project-URL: Issues, https://github.com/DAMO-NLP-SG/Inf-CLIP/issues
Requires-Python: >=3.8
Requires-Dist: numpy
Requires-Dist: triton>=2.2.0
